Simple_email/__init__.py
Simple_email/simple_email.py
simple_email-0.0.4.dist-info/LICENSE
simple_email-0.0.4.dist-info/METADATA
simple_email-0.0.4.dist-info/WHEEL
simple_email-0.0.4.dist-info/entry_points.txt
simple_email-0.0.4.dist-info/top_level.txt
simple_email-0.0.4.dist-info/RECORD
