Metadata-Version: 2.1
Name: simple-email
Version: 0.0.4
Summary: 开箱即用的邮件发送包
Home-page: https://github.com/fanfan531/simple-email
Author: ken
Author-email: 596600794@qq.com
License: MIT
Platform: UNKNOWN
Classifier: Programming Language :: Python :: Implementation :: PyPy
Provides-Extra: test
